setup.py
SYCL/__init__.py
SYCL/one.py
SYCL/two.py
SYCL.egg-info/PKG-INFO
SYCL.egg-info/SOURCES.txt
SYCL.egg-info/dependency_links.txt
SYCL.egg-info/top_level.txt