Metadata-Version: 2.1
Name: SYCL
Version: 0.0.6
Summary: hhhhh
Author: SYC
Author-email: 1831402487@qq.com
Classifier: Programming Language :: Python :: 3
Classifier: License :: OSI Approved :: MIT License
Classifier: Operating System :: OS Independent
